<annotation>
    <folder>custom_pics</folder>
    <filename>IMG_3437.jpg</filename>
    <size>
        <width>1048</width>
        <height>1398</height>
        <depth>3</depth>
    </size>
    <segmented>0</segmented>
    <object>
        <name>cactus</name>
        <pose>Unspecified</pose>
        <truncated>0</truncated>
        <occluded>0</occluded>
        <difficult>0</difficult>
        <bndbox>
            <xmin>407</xmin>
            <ymin>330</ymin>
            <xmax>692</xmax>
            <ymax>741</ymax>
        </bndbox>
    </object>
    <object>
        <name>waterdrop</name>
        <pose>Unspecified</pose>
        <truncated>0</truncated>
        <occluded>0</occluded>
        <difficult>0</difficult>
        <bndbox>
            <xmin>714</xmin>
            <ymin>420</ymin>
            <xmax>853</xmax>
            <ymax>531</ymax>
        </bndbox>
    </object>
    <object>
        <name>locker</name>
        <pose>Unspecified</pose>
        <truncated>0</truncated>
        <occluded>0</occluded>
        <difficult>0</difficult>
        <bndbox>
            <xmin>755</xmin>
            <ymin>574</ymin>
            <xmax>933</xmax>
            <ymax>824</ymax>
        </bndbox>
    </object>
    <object>
        <name>hammer</name>
        <pose>Unspecified</pose>
        <truncated>0</truncated>
        <occluded>0</occluded>
        <difficult>0</difficult>
        <bndbox>
            <xmin>561</xmin>
            <ymin>850</ymin>
            <xmax>876</xmax>
            <ymax>1075</ymax>
        </bndbox>
    </object>
    <object>
        <name>moon</name>
        <pose>Unspecified</pose>
        <truncated>0</truncated>
        <occluded>0</occluded>
        <difficult>0</difficult>
        <bndbox>
            <xmin>366</xmin>
            <ymin>782</ymin>
            <xmax>614</xmax>
            <ymax>1100</ymax>
        </bndbox>
    </object>
    <object>
        <name>splash</name>
        <pose>Unspecified</pose>
        <truncated>0</truncated>
        <occluded>0</occluded>
        <difficult>0</difficult>
        <bndbox>
            <xmin>164</xmin>
            <ymin>734</ymin>
            <xmax>323</xmax>
            <ymax>912</ymax>
        </bndbox>
    </object>
    <object>
        <name>target</name>
        <pose>Unspecified</pose>
        <truncated>0</truncated>
        <occluded>0</occluded>
        <difficult>0</difficult>
        <bndbox>
            <xmin>137</xmin>
            <ymin>508</ymin>
            <xmax>297</xmax>
            <ymax>668</ymax>
        </bndbox>
    </object>
    <object>
        <name>bird</name>
        <pose>Unspecified</pose>
        <truncated>0</truncated>
        <occluded>0</occluded>
        <difficult>0</difficult>
        <bndbox>
            <xmin>269</xmin>
            <ymin>321</ymin>
            <xmax>471</xmax>
            <ymax>488</ymax>
        </bndbox>
    </object>
</annotation>