<annotation>
    <folder>custom_pics</folder>
    <filename>IMG_3433.jpg</filename>
    <size>
        <width>1048</width>
        <height>1398</height>
        <depth>3</depth>
    </size>
    <segmented>0</segmented>
    <object>
        <name>hammer</name>
        <pose>Unspecified</pose>
        <truncated>0</truncated>
        <occluded>0</occluded>
        <difficult>0</difficult>
        <bndbox>
            <xmin>551</xmin>
            <ymin>1155</ymin>
            <xmax>730</xmax>
            <ymax>1296</ymax>
        </bndbox>
    </object>
    <object>
        <name>moon</name>
        <pose>Unspecified</pose>
        <truncated>0</truncated>
        <occluded>0</occluded>
        <difficult>0</difficult>
        <bndbox>
            <xmin>439</xmin>
            <ymin>1135</ymin>
            <xmax>578</xmax>
            <ymax>1315</ymax>
        </bndbox>
    </object>
    <object>
        <name>splash</name>
        <pose>Unspecified</pose>
        <truncated>0</truncated>
        <occluded>0</occluded>
        <difficult>0</difficult>
        <bndbox>
            <xmin>319</xmin>
            <ymin>1123</ymin>
            <xmax>407</xmax>
            <ymax>1224</ymax>
        </bndbox>
    </object>
    <object>
        <name>target</name>
        <pose>Unspecified</pose>
        <truncated>0</truncated>
        <occluded>0</occluded>
        <difficult>0</difficult>
        <bndbox>
            <xmin>293</xmin>
            <ymin>994</ymin>
            <xmax>385</xmax>
            <ymax>1088</ymax>
        </bndbox>
    </object>
    <object>
        <name>cactus</name>
        <pose>Unspecified</pose>
        <truncated>0</truncated>
        <occluded>0</occluded>
        <difficult>0</difficult>
        <bndbox>
            <xmin>447</xmin>
            <ymin>870</ymin>
            <xmax>609</xmax>
            <ymax>1111</ymax>
        </bndbox>
    </object>
    <object>
        <name>locker</name>
        <pose>Unspecified</pose>
        <truncated>0</truncated>
        <occluded>0</occluded>
        <difficult>0</difficult>
        <bndbox>
            <xmin>650</xmin>
            <ymin>998</ymin>
            <xmax>755</xmax>
            <ymax>1139</ymax>
        </bndbox>
    </object>
    <object>
        <name>waterdrop</name>
        <pose>Unspecified</pose>
        <truncated>0</truncated>
        <occluded>0</occluded>
        <difficult>0</difficult>
        <bndbox>
            <xmin>621</xmin>
            <ymin>909</ymin>
            <xmax>697</xmax>
            <ymax>977</ymax>
        </bndbox>
    </object>
    <object>
        <name>web</name>
        <pose>Unspecified</pose>
        <truncated>0</truncated>
        <occluded>0</occluded>
        <difficult>0</difficult>
        <bndbox>
            <xmin>534</xmin>
            <ymin>191</ymin>
            <xmax>645</xmax>
            <ymax>301</ymax>
        </bndbox>
    </object>
    <object>
        <name>sun</name>
        <pose>Unspecified</pose>
        <truncated>0</truncated>
        <occluded>0</occluded>
        <difficult>0</difficult>
        <bndbox>
            <xmin>496</xmin>
            <ymin>310</ymin>
            <xmax>677</xmax>
            <ymax>504</ymax>
        </bndbox>
    </object>
    <object>
        <name>igloo</name>
        <pose>Unspecified</pose>
        <truncated>0</truncated>
        <occluded>0</occluded>
        <difficult>0</difficult>
        <bndbox>
            <xmin>469</xmin>
            <ymin>494</ymin>
            <xmax>576</xmax>
            <ymax>581</ymax>
        </bndbox>
    </object>
    <object>
        <name>skull</name>
        <pose>Unspecified</pose>
        <truncated>0</truncated>
        <occluded>0</occluded>
        <difficult>0</difficult>
        <bndbox>
            <xmin>286</xmin>
            <ymin>410</ymin>
            <xmax>459</xmax>
            <ymax>569</ymax>
        </bndbox>
    </object>
    <object>
        <name>flower</name>
        <pose>Unspecified</pose>
        <truncated>0</truncated>
        <occluded>0</occluded>
        <difficult>0</difficult>
        <bndbox>
            <xmin>222</xmin>
            <ymin>316</ymin>
            <xmax>319</xmax>
            <ymax>410</ymax>
        </bndbox>
    </object>
    <object>
        <name>zebra</name>
        <pose>Unspecified</pose>
        <truncated>0</truncated>
        <occluded>0</occluded>
        <difficult>0</difficult>
        <bndbox>
            <xmin>392</xmin>
            <ymin>282</ymin>
            <xmax>481</xmax>
            <ymax>396</ymax>
        </bndbox>
    </object>
    <object>
        <name>target</name>
        <pose>Unspecified</pose>
        <truncated>0</truncated>
        <occluded>0</occluded>
        <difficult>0</difficult>
        <bndbox>
            <xmin>270</xmin>
            <ymin>180</ymin>
            <xmax>383</xmax>
            <ymax>290</ymax>
        </bndbox>
    </object>
    <object>
        <name>bird</name>
        <pose>Unspecified</pose>
        <truncated>0</truncated>
        <occluded>0</occluded>
        <difficult>0</difficult>
        <bndbox>
            <xmin>362</xmin>
            <ymin>876</ymin>
            <xmax>478</xmax>
            <ymax>977</ymax>
        </bndbox>
    </object>
    <object>
        <name>ghost</name>
        <pose>Unspecified</pose>
        <truncated>0</truncated>
        <occluded>0</occluded>
        <difficult>0</difficult>
        <bndbox>
            <xmin>434</xmin>
            <ymin>144</ymin>
            <xmax>512</xmax>
            <ymax>275</ymax>
        </bndbox>
    </object>
</annotation>