<annotation>
    <folder>custom_pics</folder>
    <filename>IMG_3487.jpg</filename>
    <size>
        <width>3024</width>
        <height>4032</height>
        <depth>3</depth>
    </size>
    <segmented>0</segmented>
    <object>
        <name>moon</name>
        <pose>Unspecified</pose>
        <truncated>0</truncated>
        <occluded>0</occluded>
        <difficult>0</difficult>
        <bndbox>
            <xmin>522</xmin>
            <ymin>1512</ymin>
            <xmax>1282</xmax>
            <ymax>2200</ymax>
        </bndbox>
    </object>
    <object>
        <name>bonfire</name>
        <pose>Unspecified</pose>
        <truncated>0</truncated>
        <occluded>0</occluded>
        <difficult>0</difficult>
        <bndbox>
            <xmin>613</xmin>
            <ymin>2176</ymin>
            <xmax>1225</xmax>
            <ymax>2614</ymax>
        </bndbox>
    </object>
    <object>
        <name>ladybug</name>
        <pose>Unspecified</pose>
        <truncated>0</truncated>
        <occluded>0</occluded>
        <difficult>0</difficult>
        <bndbox>
            <xmin>995</xmin>
            <ymin>2514</ymin>
            <xmax>1444</xmax>
            <ymax>3036</ymax>
        </bndbox>
    </object>
    <object>
        <name>horse</name>
        <pose>Unspecified</pose>
        <truncated>0</truncated>
        <occluded>0</occluded>
        <difficult>0</difficult>
        <bndbox>
            <xmin>1453</xmin>
            <ymin>2099</ymin>
            <xmax>2125</xmax>
            <ymax>2934</ymax>
        </bndbox>
    </object>
    <object>
        <name>dobble</name>
        <pose>Unspecified</pose>
        <truncated>0</truncated>
        <occluded>0</occluded>
        <difficult>0</difficult>
        <bndbox>
            <xmin>1987</xmin>
            <ymin>1944</ymin>
            <xmax>2614</xmax>
            <ymax>2412</ymax>
        </bndbox>
    </object>
    <object>
        <name>pencil</name>
        <pose>Unspecified</pose>
        <truncated>0</truncated>
        <occluded>0</occluded>
        <difficult>0</difficult>
        <bndbox>
            <xmin>1542</xmin>
            <ymin>1193</ymin>
            <xmax>2396</xmax>
            <ymax>1391</ymax>
        </bndbox>
    </object>
    <object>
        <name>flower</name>
        <pose>Unspecified</pose>
        <truncated>0</truncated>
        <occluded>0</occluded>
        <difficult>0</difficult>
        <bndbox>
            <xmin>1003</xmin>
            <ymin>1016</ymin>
            <xmax>1452</xmax>
            <ymax>1461</ymax>
        </bndbox>
    </object>
    <object>
        <name>clown</name>
        <pose>Unspecified</pose>
        <truncated>0</truncated>
        <occluded>0</occluded>
        <difficult>0</difficult>
        <bndbox>
            <xmin>1452</xmin>
            <ymin>1532</ymin>
            <xmax>1934</xmax>
            <ymax>1962</ymax>
        </bndbox>
    </object>
</annotation>